licverify/__init__.py
licverify/binary_format.py
licverify/cli.py
licverify/exceptions.py
licverify/hardware.py
licverify/license.py
licverify/py.typed
licverify/utils.py
licverify/verifier.py
python_licverify-0.2.1.dist-info/METADATA
python_licverify-0.2.1.dist-info/WHEEL
python_licverify-0.2.1.dist-info/entry_points.txt
python_licverify-0.2.1.dist-info/RECORD
