Metadata-Version: 2.4
Name: python-licverify
Version: 0.2.1
Summary: Python client for go-license license verification
Project-URL: Source, https://github.com/luhtfiimanal/python-licverify
Project-URL: Bug Tracker, https://github.com/luhtfiimanal/python-licverify/issues
Author-email: Luthfi Imanal Satrya <luthfi.imanal@gmail.com>
License: MIT
Keywords: go-license,license,rsa,verification
Classifier: License :: OSI Approved :: MIT License
Classifier: Programming Language :: Python :: 3
Classifier: Programming Language :: Python :: 3 :: Only
Classifier: Programming Language :: Python :: 3.12
Requires-Python: >=3.12
Requires-Dist: cryptography>=45.0.5
Requires-Dist: psutil>=7.0.0
